{
  "file": "ISic003486",
  "metadataFile": "metadata/ISic003486.json",
  "htmlFile": "html/ISic003486.json",
  "uri": "http://sicily.classics.ox.ac.uk/inscription/ISic003486",
  "title": "I.Sicily inscription 003486",
  "status": "draft",
  "type": {
    "_": "funerary",
    "ana": "#function.funerary",
    "ref": "http://www.eagle-network.eu/voc/typeins/lod/92.html"
  },
  "objectType": {
    "_": "stele",
    "ana": "#object.stele",
    "ref": "http://www.eagle-network.eu/voc/objtyp/lod/250.html"
  },
  "material": {
    "_": "stone",
    "ana": "#material.stone",
    "ref": "http://www.eagle-network.eu/voc/material/lod/2.html"
  },
  "layoutDesc": {
    "_": "chiselled",
    "ana": "#execution.chiselled",
    "ref": "http://www.eagle-network.eu/voc/writing/lod/1"
  },
  "notBefore": 201,
  "notAfter": 300,
  "places": [
    {
      "_": "Sicilia",
      "type": "ancient",
      "ref": "http://pleiades.stoa.org/places/462492"
    },
    {
      "_": "Sicily",
      "type": "modern",
      "ref": "http://sws.geonames.org/2523119"
    }
  ],
  "facsimile": {
    "url": "ISic003486_tiled.tif",
    "desc": "I.Sicily with the permission of the Assessorato Regionale dei Beni Culturali e dell’Identità Siciliana - Dipartimento dei Beni Culturali e dell’Identità Siciliana"
  },
  "country": "Italy",
  "region": "Sicily",
  "settlement": "Palermo",
  "textLang": {
    "_": "Ancient Greek",
    "mainLang": "grc"
  },
  "placeName": "Sicilia",
  "keywords": [
    "http://sicily.classics.ox.ac.uk/inscription/isic003486",
    "i.sicily inscription 003486",
    "draft",
    "funerary",
    "stele",
    "stone",
    "201",
    "300",
    "sicilia",
    "sicily",
    "italy",
    "sicily",
    "palermo",
    "museo archeologico\n                            regionale antonino salinas",
    "ancient greek",
    "grc"
  ]
}