{
  "file": "ISic000821",
  "metadataFile": "metadata/ISic000821.json",
  "htmlFile": "html/ISic000821.json",
  "uri": "http://sicily.classics.ox.ac.uk/inscription/ISic000821",
  "title": "Fragment of a Latin inscripton relating to building works",
  "status": "draft",
  "type": {
    "_": "building",
    "ana": "#function.building",
    "ref": "http://www.eagle-network.eu/voc/typeins/lod/86.html"
  },
  "objectType": {
    "_": "plaque",
    "ana": "#object.plaque",
    "ref": "http://www.eagle-network.eu/voc/objtyp/lod/259"
  },
  "material": {
    "_": "marble",
    "ana": "#material.stone.marble",
    "ref": "http://www.eagle-network.eu/voc/material/lod/48.html"
  },
  "notBefore": 201,
  "notAfter": 400,
  "geo": [
    37,
    15
  ],
  "facsimile": {
    "url": "ISic000821_tiled.tif",
    "desc": "I.Sicily with the permission of the Assessorato Regionale dei Beni Culturali e dell’Identità Siciliana - Dipartimento dei Beni Culturali e dell’Identità Siciliana"
  },
  "country": "Italy",
  "region": "Sicily",
  "settlement": "Catania",
  "textLang": {
    "_": "Latin",
    "mainLang": "la"
  },
  "place": {
    "_": "Catina",
    "type": "ancient",
    "ref": "http://pleiades.stoa.org/places/462270"
  },
  "placeName": "Catina",
  "keywords": [
    "http://sicily.classics.ox.ac.uk/inscription/isic000821",
    "fragment of a latin inscripton relating to building works",
    "draft",
    "building",
    "plaque",
    "marble",
    "201",
    "400",
    "catina",
    "catania",
    "italy",
    "sicily",
    "catania",
    "in storage, ex manifattura tabacchi - catania, via garibaldi, 233 , soprintendenza di catania",
    "latin",
    "la"
  ]
}