{
  "file": "ISic000921",
  "metadataFile": "metadata/ISic000921.json",
  "htmlFile": "html/ISic000921.json",
  "uri": "http://sicily.classics.ox.ac.uk/inscription/ISic000921",
  "title": "I.Sicily inscription 000921",
  "status": "draft",
  "notBefore": 400,
  "notAfter": 700,
  "facsimile": {
    "url": "ISic000921_tiled.tif",
    "desc": "I.Sicily with the permission of the Assessorato Regionale dei Beni Culturali e dell’Identità Siciliana - Dipartimento dei Beni Culturali e dell’Identità Siciliana"
  },
  "country": "Italy",
  "region": "Sicily",
  "settlement": "Siracusa",
  "repository": "",
  "textLang": {
    "_": "Ancient Greek",
    "mainLang": "grc"
  },
  "keywords": [
    "http://sicily.classics.ox.ac.uk/inscription/ISic000921",
    "I.Sicily inscription 000921",
    "draft",
    "400",
    "700",
    "Italy",
    "Sicily",
    "Siracusa",
    "Ancient Greek",
    "grc"
  ]
}