{
  "file": "ISic001701",
  "metadataFile": "metadata/ISic001701.json",
  "htmlFile": "html/ISic001701.json",
  "uri": "http://sicily.classics.ox.ac.uk/inscription/ISic001701",
  "title": "Marble votive table with Punic inscription",
  "status": "draft",
  "notBefore": -250,
  "notAfter": -50,
  "geo": "36.78333, 12",
  "facsimile": {
    "url": "ISic001701_tiled.tif",
    "desc": "Photo J. Prag, 14-01-2020"
  },
  "country": "Italy",
  "region": "Sicily",
  "settlement": "Pantelleria",
  "repository": "Pantelleria excavation store",
  "textLang": {
    "_": "Punic",
    "mainLang": "xpu"
  },
  "place": {
    "_": "Pantelleria",
    "type": "modern",
    "ref": "http://sws.geonames.org/2523889"
  },
  "placeName": "Pantelleria",
  "keywords": [
    "http://sicily.classics.ox.ac.uk/inscription/isic001701",
    "marble votive table with punic inscription",
    "draft",
    "-250",
    "-50",
    "pantelleria",
    "cossura",
    "italy",
    "sicily",
    "pantelleria",
    "punic",
    "xpu"
  ]
}