{
  "file": "ISic000759",
  "uri": "ISic000759",
  "title": "I.Sicily inscription 000759",
  "status": "edited",
  "editions": [
    {
      "_": "175795",
      "type": "TM"
    },
    {
      "type": "EDR"
    },
    {
      "type": "EDH"
    },
    {
      "_": "6100288",
      "type": "EDCS"
    },
    {
      "type": "PHI"
    }
  ],
  "type": {
    "_": "funerary",
    "ana": "#function.funerary",
    "ref": "http://www.eagle-network.eu/voc/typeins/lod/92.html"
  },
  "support": "A fragmentary altar made of limestone, damaged across the top and the right, intact front left and below.",
  "objectType": {
    "_": "altar",
    "ana": "#object.altar",
    "ref": "http://www.eagle-network.eu/voc/objtyp/lod/29.html"
  },
  "material": {
    "_": "limestone",
    "ana": "#material.stone.limestone",
    "ref": "http://www.eagle-network.eu/voc/material/lod/66.html"
  },
  "condition": {
    "ana": "#condition.damaged"
  },
  "dimensions": [
    {
      "unit": "cm",
      "dimension": "height"
    },
    {
      "unit": "cm",
      "dimension": "width"
    },
    {
      "unit": "cm",
      "dimension": "depth"
    }
  ],
  "layoutDesc": {
    "layout": {
      "p": "Text within a recessed field, surrounded by a raised border, left margin is regular and text fills the field, but the first preserved line is larger, more widely spaced.",
      "rs": {
        "_": "chiselled",
        "ana": "#execution.chiselled",
        "ref": "http://www.eagle-network.eu/voc/writing/lod/1"
      },
      "damage": {
        "ana": "#text_condition.incomplete #text_condition.legible"
      }
    }
  },
  "handNote": {
    "lettering": "Letters are broad and well-spaced, of a wide square module, with small serifs, decreasing in height towards the bottom. V appears slightly curved and sometimes over extended; M is broad, four diagonal full length strokes.",
    "dimensions": [
      {
        "type": "letterHeight",
        "l": "Line 1",
        "from": "line1",
        "to": "line1",
        "unit": "mm"
      },
      {
        "type": "interlinear",
        "l": "Interlineation line 1 to 2",
        "from": "line1",
        "to": "line2",
        "unit": "mm"
      }
    ]
  },
  "notBefore": 1,
  "notAfter": 200,
  "evidence": "lettering",
  "places": [
    {
      "_": "Enna",
      "type": "ancient",
      "ref": "http://pleiades.stoa.org/places/462236"
    },
    {
      "_": "Enna",
      "type": "modern",
      "ref": "http://sws.geonames.org/2524819"
    }
  ],
  "geo": [
    [
      37.5655,
      14.27433
    ]
  ],
  "provenanceFound": {
    "_": "Seen by Manganaro in a collection in Enna and assumed to come from the surrounding area",
    "type": "found",
    "subtype": "first-recorded",
    "notAfter": "1989",
    "geo": null
  },
  "provenanceObserved": null,
  "provenanceLost": null,
  "facsimile": {
    "url": "ISic000759_tiled.tif",
    "desc": "I.Sicily with the permission of the Assessorato Regionale dei Beni Culturali e dell’Identità Siciliana - Dipartimento dei Beni Culturali e dell’Identità Siciliana"
  },
  "country": "Italy",
  "region": "Sicily",
  "settlement": "Enna",
  "repository": "private collection",
  "textLang": {
    "_": "Latin",
    "mainLang": "la"
  },
  "bibliographyEdition": {
    "type": "edition",
    "bibl": [
      {
        "type": "bulletin",
        "n": "AE",
        "citedRange": "1989.0344b",
        "ptr": {
          "target": "http://zotero.org/groups/382445/items/R46KDTZX"
        },
        "ref": {
          "_": "https://biblio.inscriptiones.org/epig10001283",
          "target": "https://biblio.inscriptiones.org/epig10001283"
        }
      },
      {
        "author": "Manganaro",
        "date": "1989",
        "citedRange": "186 no.72 fig.77",
        "ptr": {
          "target": "https://www.zotero.org/groups/382445/items/EZMBJ6GN"
        },
        "ref": {
          "_": "https://biblio.inscriptiones.org/epig10001831",
          "target": "https://biblio.inscriptiones.org/epig10001831"
        }
      }
    ]
  },
  "bibliographyDiscussion": {
    "type": "discussion",
    "bibl": ""
  },
  "placeName": "Enna",
  "keywords": [
    "isic000759",
    "i.sicily inscription 000759",
    "edited",
    "funerary",
    "altar",
    "limestone",
    "1",
    "200",
    "enna",
    "enna",
    "italy",
    "sicily",
    "enna",
    "latin",
    "la"
  ]
}