{
  "file": "ISic003354",
  "metadataFile": "metadata/ISic003354.json",
  "htmlFile": "html/ISic003354.json",
  "uri": "http://sicily.classics.ox.ac.uk/inscription/ISic003354",
  "title": "I.Sicily inscription 003354",
  "status": "draft",
  "notBefore": 150,
  "notAfter": 200,
  "geo": "36.04528, 14.24167",
  "facsimile": {
    "url": "ISic003354_tiled.tif",
    "desc": "I.Sicily with the permission of the Assessorato Regionale dei Beni Culturali e dell’Identità Siciliana - Dipartimento dei Beni Culturali e dell’Identità Siciliana"
  },
  "country": "Italy",
  "region": "Sicily",
  "settlement": "Gozo",
  "repository": "",
  "textLang": {
    "_": "Latin",
    "mainLang": "la"
  },
  "place": {
    "_": "Gozo",
    "type": "modern",
    "ref": "http://sws.geonames.org/2563049"
  },
  "placeName": "Gozo",
  "keywords": [
    "http://sicily.classics.ox.ac.uk/inscription/isic003354",
    "i.sicily inscription 003354",
    "draft",
    "150",
    "200",
    "gozo",
    "gaulus",
    "italy",
    "sicily",
    "gozo",
    "latin",
    "la"
  ]
}