{
  "file": "ISic000472",
  "metadataFile": "metadata/ISic000472.json",
  "htmlFile": "html/ISic000472.json",
  "uri": "http://sicily.classics.ox.ac.uk/inscription/ISic000472",
  "title": "I.Sicily inscription 000472",
  "status": "draft",
  "type": {
    "_": "unknown",
    "ana": "#function.unknown",
    "ref": "https://www.eagle-network.eu/voc/objtyp/lod/2.html"
  },
  "objectType": {
    "_": "plaque",
    "ana": "#object.plaque",
    "ref": "http://www.eagle-network.eu/voc/objtyp/lod/259.html"
  },
  "material": {
    "_": "marble (white)",
    "ana": "#material.stone.marble",
    "ref": "http://www.eagle-network.eu/voc/material/lod/48.html"
  },
  "layoutDesc": {
    "_": "chiselled",
    "ana": "#execution.chiselled",
    "ref": "http://www.eagle-network.eu/voc/writing/lod/1"
  },
  "letterHeight": [
    {
      "l": "Line 1",
      "from": "line1",
      "to": "line1",
      "unit": "mm"
    }
  ],
  "notBefore": 1,
  "notAfter": 300,
  "places": [
    {
      "_": "Tyndaris",
      "type": "ancient",
      "ref": "http://pleiades.stoa.org/places/462527"
    },
    {
      "_": "Tindari",
      "type": "modern",
      "ref": "http://sws.geonames.org/10282151"
    }
  ],
  "geo": [
    38.14227,
    15.04385
  ],
  "facsimile": {
    "url": "ISic000472_tiled.tif",
    "desc": "I.Sicily with the permission of the Assessorato Regionale dei Beni Culturali e dell’Identità Siciliana - Dipartimento dei Beni Culturali e dell’Identità Siciliana"
  },
  "country": "Italy",
  "region": "Sicily",
  "settlement": "Palermo",
  "textLang": {
    "_": "Latin",
    "mainLang": "la"
  },
  "placeName": "Tyndaris",
  "keywords": [
    "http://sicily.classics.ox.ac.uk/inscription/isic000472",
    "i.sicily inscription 000472",
    "draft",
    "unknown",
    "plaque",
    "marble (white)",
    "1",
    "300",
    "tyndaris",
    "tindari",
    "italy",
    "sicily",
    "palermo",
    "museo archeologico regionale antonino salinas",
    "latin",
    "la"
  ]
}