{
  "file": "ISic001114",
  "metadataFile": "metadata/ISic001114.json",
  "htmlFile": "html/ISic001114.json",
  "uri": "http://sicily.classics.ox.ac.uk/inscription/ISic001114",
  "title": "I.Sicily inscription 001114",
  "status": "draft",
  "notBefore": -300,
  "notAfter": -1,
  "place": {
    "_": "Monte Iato",
    "type": "modern",
    "ref": "http://sws.geonames.org/2524540"
  },
  "placeName": "Monte Iato",
  "geo": "37.967050, 13.198199",
  "facsimile": {
    "url": "ISic001114_tiled.tif",
    "desc": "I.Sicily with the permission of the Assessorato Regionale dei Beni Culturali e dell’Identità Siciliana - Dipartimento dei Beni Culturali e dell’Identità Siciliana"
  },
  "country": "Italy",
  "region": "Sicily",
  "settlement": "Alcamo",
  "repository": "",
  "textLang": {
    "_": "Ancient Greek",
    "mainLang": "grc"
  },
  "keywords": [
    "http://sicily.classics.ox.ac.uk/inscription/isic001114",
    "i.sicily inscription 001114",
    "draft",
    "-300",
    "-1",
    "monte iato",
    "ietas",
    "italy",
    "sicily",
    "alcamo",
    "ancient greek",
    "grc"
  ]
}