{
  "file": "ISic003016",
  "metadataFile": "metadata/ISic003016.json",
  "htmlFile": "html/ISic003016.json",
  "uri": "http://sicily.classics.ox.ac.uk/inscription/ISic003016",
  "title": "I.Sicily inscription 003016",
  "status": "draft",
  "type": {
    "_": "dedication",
    "ana": "#function.dedication",
    "ref": "http://www.eagle-network.eu/voc/typeins/lod/88.html"
  },
  "notBefore": -50,
  "notAfter": -1,
  "geo": [
    37,
    14
  ],
  "facsimile": {
    "url": "ISic003016_tiled.tif",
    "desc": "I.Sicily with the permission of the Assessorato Regionale dei Beni Culturali e dell’Identità Siciliana - Dipartimento dei Beni Culturali e dell’Identità Siciliana"
  },
  "country": "Italy",
  "region": "Sicily",
  "settlement": "Siracusa",
  "textLang": {
    "_": "Ancient Greek",
    "mainLang": "grc"
  },
  "place": {
    "_": "Buscemi",
    "type": "modern",
    "ref": "http://pleiades.stoa.org/places/462120"
  },
  "placeName": "Buscemi",
  "keywords": [
    "http://sicily.classics.ox.ac.uk/inscription/isic003016",
    "i.sicily inscription 003016",
    "draft",
    "-50",
    "-1",
    "buscemi",
    "italy",
    "sicily",
    "siracusa",
    "museo archeologico\n                            regionale paolo orsi",
    "ancient greek",
    "grc"
  ]
}