{
  "title": "ISic000409. I.Sicily inscription 000409",
  "body": "<div id=\"editions\"><div id=\"edition-interpretive\" lang=\"la\">  <div class=\"textpart\" lang=\"la\"><span class=\"ab\" id=\"div-interpretive\">  <a id=\"al1-interpretive\"><!--0--></a><span class=\"linenumber\">1</span>Dis · Ma<span class=\"petraeligature\" title=\"Ligature: these characters are joined\">n͡i</span>b(us) · <br id=\"al2-interpretive\"><span class=\"linenumber\">2</span>C(aius) · Iul<span class=\"petraeligature\" title=\"Ligature: these characters are joined\">i͡u</span>s · P<span class=\"petraeligature\" title=\"Ligature: these characters are joined\">r͡i</span><span class=\"petraeligature\" title=\"Ligature: these characters are joined\">m͡i</span>o <br id=\"al3-interpretive\"><span class=\"linenumber\">3</span>Isidis · scop<span class=\"petraeligature\" title=\"Ligature: these characters are joined\">a͡r</span>(ius) <br id=\"al4-interpretive\"><span class=\"linenumber\">4</span>vix(it) · ann(os) · LXXX <br id=\"al5-interpretive\"><span class=\"linenumber\">5</span>pie · salve </span></div>  <p class=\"miniapp\">l.2 superscript</p></div><div id=\"edition-diplomatic\" lang=\"la\"><div class=\"textpart\" lang=\"la\"><span class=\"ab\" id=\"div-diplomatic\"><a id=\"al1-diplomatic\"><!--0--></a><span class=\"linenumber\">1</span>DISMA<span class=\"petraeligature\" title=\"Ligature: these characters are joined\">N͡I</span>B<br id=\"al2-diplomatic\"><span class=\"linenumber\">2</span>CIUL<span class=\"petraeligature\" title=\"Ligature: these characters are joined\">I͡U</span>SP<span class=\"petraeligature\" title=\"Ligature: these characters are joined\">R͡I</span><span class=\"petraeligature\" title=\"Ligature: these characters are joined\">M͡I</span>O<br id=\"al3-diplomatic\"><span class=\"linenumber\">3</span>ISIDISSCOP<span class=\"petraeligature\" title=\"Ligature: these characters are joined\">A͡R</span><br id=\"al4-diplomatic\"><span class=\"linenumber\">4</span>VIXANNLXXX<br id=\"al5-diplomatic\"><span class=\"linenumber\">5</span>PIESALVE</span></div><p class=\"miniapp\">l.2 superscript</p></div></div>  <div id=\"facsimile-images\"><h2>Facsimile Images</h2><a href=\"ISic000409_tiled.tif\"><img title=\"Museum archive photograph\" src=\"ISic000409_tiled-thumb.tif\"></a><a href=\"ISic000409.jpg\"><img title=\"Museum archive photograph\" src=\"ISic000409-thumb.jpg\"></a></div>  <div id=\"apparatus\"><h4>Apparatus criticus</h4><ul><li><span><span>Text transcribed from photograph</span></span></li></ul></div>  <div id=\"translation\"><h2> translation</h2><p class=\"translation-author\">  </p><p>  </p></div>  <div id=\"commentary\"><h2>commentary</h2>  <p>  </p>  </div>  <div id=\"bibliography\"><h2>bibliography</h2>  <ul><li> 4416 <a href=\"https://biblio.inscriptiones.org/epig10000352\" target=\"_blank\">https://biblio.inscriptiones.org/epig10000352</a></li><li> Mommsen 1883 <a href=\"http://arachne.uni-koeln.de/books/CILv10pII1883\" target=\"_blank\">7129</a>  <a href=\"https://biblio.inscriptiones.org/epig10000589\" target=\"_blank\">https://biblio.inscriptiones.org/epig10000589</a></li><li> Manganaro 1961 176 no.8 ph <a href=\"https://biblio.inscriptiones.org/epig10001852\" target=\"_blank\">https://biblio.inscriptiones.org/epig10001852</a></li><li> Manganaro 1989 182 no.62 <a href=\"https://biblio.inscriptiones.org/epig10001831\" target=\"_blank\">https://biblio.inscriptiones.org/epig10001831</a></li></ul>  <ul><li></li></ul>  </div>  <div id=\"license\"> Licensed under a Creative Commons-Attribution 4.0 licence.  </div>",
  "divs": [
    {
      "id": "editions",
      "html": "<div id=\"edition-interpretive\" lang=\"la\">  <div class=\"textpart\" lang=\"la\"><span class=\"ab\" id=\"div-interpretive\">  <a id=\"al1-interpretive\"><!--0--></a><span class=\"linenumber\">1</span>Dis · Ma<span class=\"petraeligature\" title=\"Ligature: these characters are joined\">n͡i</span>b(us) · <br id=\"al2-interpretive\"><span class=\"linenumber\">2</span>C(aius) · Iul<span class=\"petraeligature\" title=\"Ligature: these characters are joined\">i͡u</span>s · P<span class=\"petraeligature\" title=\"Ligature: these characters are joined\">r͡i</span><span class=\"petraeligature\" title=\"Ligature: these characters are joined\">m͡i</span>o <br id=\"al3-interpretive\"><span class=\"linenumber\">3</span>Isidis · scop<span class=\"petraeligature\" title=\"Ligature: these characters are joined\">a͡r</span>(ius) <br id=\"al4-interpretive\"><span class=\"linenumber\">4</span>vix(it) · ann(os) · LXXX <br id=\"al5-interpretive\"><span class=\"linenumber\">5</span>pie · salve </span></div>  <p class=\"miniapp\">l.2 superscript</p></div><div id=\"edition-diplomatic\" lang=\"la\"><div class=\"textpart\" lang=\"la\"><span class=\"ab\" id=\"div-diplomatic\"><a id=\"al1-diplomatic\"><!--0--></a><span class=\"linenumber\">1</span>DISMA<span class=\"petraeligature\" title=\"Ligature: these characters are joined\">N͡I</span>B<br id=\"al2-diplomatic\"><span class=\"linenumber\">2</span>CIUL<span class=\"petraeligature\" title=\"Ligature: these characters are joined\">I͡U</span>SP<span class=\"petraeligature\" title=\"Ligature: these characters are joined\">R͡I</span><span class=\"petraeligature\" title=\"Ligature: these characters are joined\">M͡I</span>O<br id=\"al3-diplomatic\"><span class=\"linenumber\">3</span>ISIDISSCOP<span class=\"petraeligature\" title=\"Ligature: these characters are joined\">A͡R</span><br id=\"al4-diplomatic\"><span class=\"linenumber\">4</span>VIXANNLXXX<br id=\"al5-diplomatic\"><span class=\"linenumber\">5</span>PIESALVE</span></div><p class=\"miniapp\">l.2 superscript</p></div>"
    },
    {
      "id": "apparatus",
      "html": "<h4>Apparatus criticus</h4><ul><li><span><span>Text transcribed from photograph</span></span></li></ul>"
    },
    {
      "id": "translation",
      "html": "<h2> translation</h2><p class=\"translation-author\">  </p><p>  </p>"
    },
    {
      "id": "commentary",
      "html": "<h2>commentary</h2>  <p>  </p>  "
    },
    {
      "id": "bibliography",
      "html": "<h2>bibliography</h2>  <ul><li> 4416 <a href=\"https://biblio.inscriptiones.org/epig10000352\" target=\"_blank\">https://biblio.inscriptiones.org/epig10000352</a></li><li> Mommsen 1883 <a href=\"http://arachne.uni-koeln.de/books/CILv10pII1883\" target=\"_blank\">7129</a>  <a href=\"https://biblio.inscriptiones.org/epig10000589\" target=\"_blank\">https://biblio.inscriptiones.org/epig10000589</a></li><li> Manganaro 1961 176 no.8 ph <a href=\"https://biblio.inscriptiones.org/epig10001852\" target=\"_blank\">https://biblio.inscriptiones.org/epig10001852</a></li><li> Manganaro 1989 182 no.62 <a href=\"https://biblio.inscriptiones.org/epig10001831\" target=\"_blank\">https://biblio.inscriptiones.org/epig10001831</a></li></ul>  <ul><li></li></ul>  "
    },
    {
      "id": "license",
      "html": " Licensed under a Creative Commons-Attribution 4.0 licence.  "
    }
  ],
  "editions": [
    {
      "id": "edition-interpretive",
      "lang": "la",
      "html": "<div class=\"textpart\" lang=\"la\"><span class=\"ab\" id=\"div-interpretive\">  <a id=\"al1-interpretive\"><!--0--></a><span class=\"linenumber\">1</span>Dis · Ma<span class=\"petraeligature\" title=\"Ligature: these characters are joined\">n͡i</span>b(us) · <br id=\"al2-interpretive\"><span class=\"linenumber\">2</span>C(aius) · Iul<span class=\"petraeligature\" title=\"Ligature: these characters are joined\">i͡u</span>s · P<span class=\"petraeligature\" title=\"Ligature: these characters are joined\">r͡i</span><span class=\"petraeligature\" title=\"Ligature: these characters are joined\">m͡i</span>o <br id=\"al3-interpretive\"><span class=\"linenumber\">3</span>Isidis · scop<span class=\"petraeligature\" title=\"Ligature: these characters are joined\">a͡r</span>(ius) <br id=\"al4-interpretive\"><span class=\"linenumber\">4</span>vix(it) · ann(os) · LXXX <br id=\"al5-interpretive\"><span class=\"linenumber\">5</span>pie · salve </span></div>  <p class=\"miniapp\">l.2 superscript</p>"
    },
    {
      "id": "edition-diplomatic",
      "lang": "la",
      "html": "<div class=\"textpart\" lang=\"la\"><span class=\"ab\" id=\"div-diplomatic\"><a id=\"al1-diplomatic\"><!--0--></a><span class=\"linenumber\">1</span>DISMA<span class=\"petraeligature\" title=\"Ligature: these characters are joined\">N͡I</span>B<br id=\"al2-diplomatic\"><span class=\"linenumber\">2</span>CIUL<span class=\"petraeligature\" title=\"Ligature: these characters are joined\">I͡U</span>SP<span class=\"petraeligature\" title=\"Ligature: these characters are joined\">R͡I</span><span class=\"petraeligature\" title=\"Ligature: these characters are joined\">M͡I</span>O<br id=\"al3-diplomatic\"><span class=\"linenumber\">3</span>ISIDISSCOP<span class=\"petraeligature\" title=\"Ligature: these characters are joined\">A͡R</span><br id=\"al4-diplomatic\"><span class=\"linenumber\">4</span>VIXANNLXXX<br id=\"al5-diplomatic\"><span class=\"linenumber\">5</span>PIESALVE</span></div><p class=\"miniapp\">l.2 superscript</p>"
    }
  ],
  "images": [
    {
      "image": "ISic000409_tiled.tif",
      "thumb": "ISic000409_tiled-thumb.tif",
      "title": "Museum archive photograph"
    },
    {
      "image": "ISic000409.jpg",
      "thumb": "ISic000409-thumb.jpg",
      "title": "Museum archive photograph"
    }
  ]
}