{
  "title": "ISic000116. I.Sicily inscription 000116",
  "body": "  <div id=\"facsimile-images\"><h2>Facsimile Images</h2><a href=\"ISic000116_tiled.tif\"><img title=\"I.Sicily with the permission of the Assessorato Regionale dei Beni Culturali e dell’Identità Siciliana - Dipartimento dei Beni Culturali e dell’Identità Siciliana; scanned from ILTermini\" src=\"ISic000116_tiled-thumb.tif\"></a><a href=\"ISic000116.jpg\"><img title=\"I.Sicily with the permission of the Assessorato Regionale dei Beni Culturali e dell’Identità Siciliana - Dipartimento dei Beni Culturali e dell’Identità Siciliana; scanned from ILTermini\" src=\"ISic000116-thumb.jpg\"></a></div>  <div id=\"edition\" lang=\"la\">  <div class=\"textpart\" lang=\"la\"><span class=\"ab\">  <a id=\"al1\"><!--0--></a>Musice <br id=\"al2\">Viboniensis <br id=\"al3\">ann(orum) ((·)) <span class=\"latinnum\">XXVI</span>  </span></div>  </div>  <div id=\"apparatus\"><h4>Apparatus criticus</h4><p>  <span class=\"\"><span>Text of ILTermini</span></span>  </p></div>  <div id=\"translation\"><h2>English translation</h2>  <p>Musice, from Vibo (Valentia), aged 26</p>  </div>  <div id=\"commentary\"><h2>commentary</h2>  <p>The name is assumed to be a female Greek name, with the Greek nominative ending in -e (Manganaro however considered the name to be masculine).</p>  </div>  <div id=\"bibliography\"><h2>bibliography</h2>  <ul>  <li> Gualtherus 1624 no. 93 <a href=\"https://biblio.inscriptiones.org/epig10002388\" target=\"_blank\">https://biblio.inscriptiones.org/epig10002388</a>  </li>  <li> Gualtherus 1624 [1625] no. 256 <a href=\"https://biblio.inscriptiones.org/epig10001931\" target=\"_blank\">https://biblio.inscriptiones.org/epig10001931</a>  </li>  <li> Castelli 1769 58 cl.6 no.7 <a href=\"https://biblio.inscriptiones.org/epig10002084\" target=\"_blank\">https://biblio.inscriptiones.org/epig10002084</a>  </li>  <li> Castelli 1784 63 cl.6 no.10 <a href=\"https://biblio.inscriptiones.org/epig10002083\" target=\"_blank\">https://biblio.inscriptiones.org/epig10002083</a>  </li>  <li>  <a href=\"http://arachne.uni-koeln.de/item/buchseite/650797\" target=\"_blank\">10.7365</a>  <a href=\"https://biblio.inscriptiones.org/epig10000589\" target=\"_blank\">https://biblio.inscriptiones.org/epig10000589</a>  </li>  <li> 34 <a href=\"https://biblio.inscriptiones.org/epig10002137\" target=\"_blank\">https://biblio.inscriptiones.org/epig10002137</a>  </li>  <li> Manganaro 1988 49 and tav.18.27 <a href=\"https://biblio.inscriptiones.org/epig10001427\" target=\"_blank\">https://biblio.inscriptiones.org/epig10001427</a>  </li>  </ul>  <ul><li></li></ul>  </div>  <div id=\"license\"> Licensed under a Creative Commons-Attribution 4.0 licence. </div>",
  "divs": [
    {
      "id": "edition",
      "html": "  <div class=\"textpart\" lang=\"la\"><span class=\"ab\">  <a id=\"al1\"><!--0--></a>Musice <br id=\"al2\">Viboniensis <br id=\"al3\">ann(orum) ((·)) <span class=\"latinnum\">XXVI</span>  </span></div>  "
    },
    {
      "id": "apparatus",
      "html": "<h4>Apparatus criticus</h4><p>  <span class=\"\"><span>Text of ILTermini</span></span>  </p>"
    },
    {
      "id": "translation",
      "html": "<h2>English translation</h2>  <p>Musice, from Vibo (Valentia), aged 26</p>  "
    },
    {
      "id": "commentary",
      "html": "<h2>commentary</h2>  <p>The name is assumed to be a female Greek name, with the Greek nominative ending in -e (Manganaro however considered the name to be masculine).</p>  "
    },
    {
      "id": "bibliography",
      "html": "<h2>bibliography</h2>  <ul>  <li> Gualtherus 1624 no. 93 <a href=\"https://biblio.inscriptiones.org/epig10002388\" target=\"_blank\">https://biblio.inscriptiones.org/epig10002388</a>  </li>  <li> Gualtherus 1624 [1625] no. 256 <a href=\"https://biblio.inscriptiones.org/epig10001931\" target=\"_blank\">https://biblio.inscriptiones.org/epig10001931</a>  </li>  <li> Castelli 1769 58 cl.6 no.7 <a href=\"https://biblio.inscriptiones.org/epig10002084\" target=\"_blank\">https://biblio.inscriptiones.org/epig10002084</a>  </li>  <li> Castelli 1784 63 cl.6 no.10 <a href=\"https://biblio.inscriptiones.org/epig10002083\" target=\"_blank\">https://biblio.inscriptiones.org/epig10002083</a>  </li>  <li>  <a href=\"http://arachne.uni-koeln.de/item/buchseite/650797\" target=\"_blank\">10.7365</a>  <a href=\"https://biblio.inscriptiones.org/epig10000589\" target=\"_blank\">https://biblio.inscriptiones.org/epig10000589</a>  </li>  <li> 34 <a href=\"https://biblio.inscriptiones.org/epig10002137\" target=\"_blank\">https://biblio.inscriptiones.org/epig10002137</a>  </li>  <li> Manganaro 1988 49 and tav.18.27 <a href=\"https://biblio.inscriptiones.org/epig10001427\" target=\"_blank\">https://biblio.inscriptiones.org/epig10001427</a>  </li>  </ul>  <ul><li></li></ul>  "
    },
    {
      "id": "license",
      "html": " Licensed under a Creative Commons-Attribution 4.0 licence. "
    }
  ],
  "images": [
    {
      "image": "ISic000116_tiled.tif",
      "thumb": "ISic000116_tiled-thumb.tif",
      "title": "I.Sicily with the permission of the Assessorato Regionale dei Beni Culturali e dell’Identità Siciliana - Dipartimento dei Beni Culturali e dell’Identità Siciliana; scanned from ILTermini"
    },
    {
      "image": "ISic000116.jpg",
      "thumb": "ISic000116-thumb.jpg",
      "title": "I.Sicily with the permission of the Assessorato Regionale dei Beni Culturali e dell’Identità Siciliana - Dipartimento dei Beni Culturali e dell’Identità Siciliana; scanned from ILTermini"
    }
  ]
}