{
  "title": "ISic004490. fragmentary funerary inscription",
  "body": "<div id=\"editions\"><div id=\"edition-interpretive\" lang=\"grc\">  <div class=\"textpart\" lang=\"grc\"><span class=\"ab\" id=\"div-interpretive\">  <a id=\"al1-interpretive\"><!--0--></a><span class=\"linenumber\">1</span>ἀνε[παύσατο<span dir=\"ltr\" class=\"gap\">---</span>] <br id=\"al2-interpretive\"><span class=\"linenumber\">2</span>ΑΦΡ[<span dir=\"ltr\" class=\"gap\">---</span>] <br id=\"al3-interpretive\"><span class=\"linenumber\">3</span>τελε̣[υτησ<span dir=\"ltr\" class=\"gap\">---</span>] <br id=\"al4-interpretive\"><span class=\"linenumber\">4</span>κιτε Ι[<span dir=\"ltr\" class=\"gap\">---</span>] </span></div>  <p class=\"miniapp\"></p></div><div id=\"edition-diplomatic\" lang=\"grc\"><div class=\"textpart\" lang=\"grc\"><span class=\"ab\" id=\"div-diplomatic\"><a id=\"al1-diplomatic\"><!--0--></a><span class=\"linenumber\">1</span>ΑΝΕ[.......<span dir=\"ltr\" class=\"gap\">---</span>]<br id=\"al2-diplomatic\"><span class=\"linenumber\">2</span>ΑΦΡ[<span dir=\"ltr\" class=\"gap\">---</span>]<br id=\"al3-diplomatic\"><span class=\"linenumber\">3</span>ΤΕΛ.[....<span dir=\"ltr\" class=\"gap\">---</span>]<br id=\"al4-diplomatic\"><span class=\"linenumber\">4</span>ΚΙΤΕΙ[<span dir=\"ltr\" class=\"gap\">---</span>]</span></div><p class=\"miniapp\"></p></div></div>  <div id=\"facsimile-images\"><h2>Facsimile Images</h2></div>  <div id=\"apparatus\"><h4>Apparatus criticus</h4><ul><li><span><span>Text of IG 14.443.3</span></span></li></ul></div>  <div id=\"translation\"><h2> translation</h2><p class=\"translation-author\">  </p><p>  </p></div>  <div id=\"commentary\"><h2>commentary</h2>  <p>  </p></div>  <div id=\"bibliography\"><h2>bibliography</h2>  <ul><li>  <a href=\"https://clio.columbia.edu/catalog/6873760\" target=\"_blank\">14.0443.3</a>  <a href=\"https://biblio.inscriptiones.org/epig10001072\" target=\"_blank\">https://biblio.inscriptiones.org/epig10001072</a></li><li> Rizzo 1904 113-114 <a href=\"https://biblio.inscriptiones.org/epig10003144\" target=\"_blank\">https://biblio.inscriptiones.org/epig10003144</a>  </li><li> Muscolino 2011-2012 229 G16 <a href=\"https://biblio.inscriptiones.org/epig10002215\" target=\"_blank\">https://biblio.inscriptiones.org/epig10002215</a>  </li></ul>  <ul><li></li></ul>  </div>  <div id=\"license\"> Licensed under a Creative Commons-Attribution 4.0 licence. </div>",
  "divs": [
    {
      "id": "editions",
      "html": "<div id=\"edition-interpretive\" lang=\"grc\">  <div class=\"textpart\" lang=\"grc\"><span class=\"ab\" id=\"div-interpretive\">  <a id=\"al1-interpretive\"><!--0--></a><span class=\"linenumber\">1</span>ἀνε[παύσατο<span dir=\"ltr\" class=\"gap\">---</span>] <br id=\"al2-interpretive\"><span class=\"linenumber\">2</span>ΑΦΡ[<span dir=\"ltr\" class=\"gap\">---</span>] <br id=\"al3-interpretive\"><span class=\"linenumber\">3</span>τελε̣[υτησ<span dir=\"ltr\" class=\"gap\">---</span>] <br id=\"al4-interpretive\"><span class=\"linenumber\">4</span>κιτε Ι[<span dir=\"ltr\" class=\"gap\">---</span>] </span></div>  <p class=\"miniapp\"></p></div><div id=\"edition-diplomatic\" lang=\"grc\"><div class=\"textpart\" lang=\"grc\"><span class=\"ab\" id=\"div-diplomatic\"><a id=\"al1-diplomatic\"><!--0--></a><span class=\"linenumber\">1</span>ΑΝΕ[.......<span dir=\"ltr\" class=\"gap\">---</span>]<br id=\"al2-diplomatic\"><span class=\"linenumber\">2</span>ΑΦΡ[<span dir=\"ltr\" class=\"gap\">---</span>]<br id=\"al3-diplomatic\"><span class=\"linenumber\">3</span>ΤΕΛ.[....<span dir=\"ltr\" class=\"gap\">---</span>]<br id=\"al4-diplomatic\"><span class=\"linenumber\">4</span>ΚΙΤΕΙ[<span dir=\"ltr\" class=\"gap\">---</span>]</span></div><p class=\"miniapp\"></p></div>"
    },
    {
      "id": "apparatus",
      "html": "<h4>Apparatus criticus</h4><ul><li><span><span>Text of IG 14.443.3</span></span></li></ul>"
    },
    {
      "id": "translation",
      "html": "<h2> translation</h2><p class=\"translation-author\">  </p><p>  </p>"
    },
    {
      "id": "commentary",
      "html": "<h2>commentary</h2>  <p>  </p>"
    },
    {
      "id": "bibliography",
      "html": "<h2>bibliography</h2>  <ul><li>  <a href=\"https://clio.columbia.edu/catalog/6873760\" target=\"_blank\">14.0443.3</a>  <a href=\"https://biblio.inscriptiones.org/epig10001072\" target=\"_blank\">https://biblio.inscriptiones.org/epig10001072</a></li><li> Rizzo 1904 113-114 <a href=\"https://biblio.inscriptiones.org/epig10003144\" target=\"_blank\">https://biblio.inscriptiones.org/epig10003144</a>  </li><li> Muscolino 2011-2012 229 G16 <a href=\"https://biblio.inscriptiones.org/epig10002215\" target=\"_blank\">https://biblio.inscriptiones.org/epig10002215</a>  </li></ul>  <ul><li></li></ul>  "
    },
    {
      "id": "license",
      "html": " Licensed under a Creative Commons-Attribution 4.0 licence. "
    }
  ],
  "images": []
}