{
  "title": "ISic002946. Dedication to Artemis",
  "body": "  <div id=\"facsimile-images\"><h2>Facsimile Images</h2><a href=\"ISic002946_tiled.tif\"><img title=\"I.Sicily with the permission of the Assessorato Regionale dei Beni Culturali e dell’Identità Siciliana - Dipartimento dei Beni Culturali e dell’Identità Siciliana\" src=\"ISic002946_tiled-thumb.tif\"></a><a href=\"ISic002946.jpg\"><img title=\"I.Sicily with the permission of the Assessorato Regionale dei Beni Culturali e dell’Identità Siciliana - Dipartimento dei Beni Culturali e dell’Identità Siciliana\" src=\"ISic002946-thumb.jpg\"></a></div>  <div id=\"edition\" lang=\"grc\"><div class=\"textpart\" lang=\"grc\"><span class=\"ab\" id=\"div\"><a id=\"al1\"><!--0--></a><span class=\"linenumber\">1</span>ΕΠΙΔΙΝΥΣΙΟΥΙ[.....]<br id=\"al2\"><span class=\"linenumber\">2</span>ΦΙΛΟΚΡΑΤΗΣΚΑΙΞ[....?]<br id=\"al3\"><span class=\"linenumber\">3</span>ΑΡΤΕΜΙΤΙΕΥ[...]</span></div></div>  <div id=\"apparatus\"><h4>Apparatus criticus</h4><p>  <span class=\"\"><span>Text of Manganaro 1965</span></span>  </p></div>  <div id=\"translation\"><h2> translation</h2>  <p>In the priesthood of Dionysios. Philokrates and Xenon(?), (made) a vow to Artemis</p>  </div>  <div id=\"commentary\"><h2>commentary</h2>  <p>Classified as a fake by Kaibel, without autopsy, both Orsi and Manganaro's autopsy confirms the text as genuine</p>  </div>  <div id=\"bibliography\"><h2>bibliography</h2>  <ul>  <li>  <a href=\"https://clio.columbia.edu/catalog/6873760\" target=\"_blank\"> 14.0012*</a>  <a href=\"https://biblio.inscriptiones.org/epig10001072\" target=\"_blank\">https://biblio.inscriptiones.org/epig10001072</a></li>  <li> Soraci 1958 253 <a href=\"https://biblio.inscriptiones.org/epig10001571\" target=\"_blank\">https://biblio.inscriptiones.org/epig10001571</a></li>  <li> Manganaro 1963 57 n.42 <a href=\"https://biblio.inscriptiones.org/epig10001850\" target=\"_blank\">https://biblio.inscriptiones.org/epig10001850</a></li>  <li> Orsi 1900 55 no. 27 <a href=\"https://biblio.inscriptiones.org/epig10001707\" target=\"_blank\">https://biblio.inscriptiones.org/epig10001707</a></li>  <li> Manganaro 1965 176 fig.5 <a href=\"https://biblio.inscriptiones.org/epig10001452\" target=\"_blank\">https://biblio.inscriptiones.org/epig10001452</a></li>  </ul>  <ul><li></li></ul>  </div>  <div id=\"license\"> Licensed under a Creative Commons-Attribution 4.0 licence.  </div>",
  "divs": [
    {
      "id": "edition",
      "html": "<div class=\"textpart\" lang=\"grc\"><span class=\"ab\" id=\"div\"><a id=\"al1\"><!--0--></a><span class=\"linenumber\">1</span>ΕΠΙΔΙΝΥΣΙΟΥΙ[.....]<br id=\"al2\"><span class=\"linenumber\">2</span>ΦΙΛΟΚΡΑΤΗΣΚΑΙΞ[....?]<br id=\"al3\"><span class=\"linenumber\">3</span>ΑΡΤΕΜΙΤΙΕΥ[...]</span></div>"
    },
    {
      "id": "apparatus",
      "html": "<h4>Apparatus criticus</h4><p>  <span class=\"\"><span>Text of Manganaro 1965</span></span>  </p>"
    },
    {
      "id": "translation",
      "html": "<h2> translation</h2>  <p>In the priesthood of Dionysios. Philokrates and Xenon(?), (made) a vow to Artemis</p>  "
    },
    {
      "id": "commentary",
      "html": "<h2>commentary</h2>  <p>Classified as a fake by Kaibel, without autopsy, both Orsi and Manganaro's autopsy confirms the text as genuine</p>  "
    },
    {
      "id": "bibliography",
      "html": "<h2>bibliography</h2>  <ul>  <li>  <a href=\"https://clio.columbia.edu/catalog/6873760\" target=\"_blank\"> 14.0012*</a>  <a href=\"https://biblio.inscriptiones.org/epig10001072\" target=\"_blank\">https://biblio.inscriptiones.org/epig10001072</a></li>  <li> Soraci 1958 253 <a href=\"https://biblio.inscriptiones.org/epig10001571\" target=\"_blank\">https://biblio.inscriptiones.org/epig10001571</a></li>  <li> Manganaro 1963 57 n.42 <a href=\"https://biblio.inscriptiones.org/epig10001850\" target=\"_blank\">https://biblio.inscriptiones.org/epig10001850</a></li>  <li> Orsi 1900 55 no. 27 <a href=\"https://biblio.inscriptiones.org/epig10001707\" target=\"_blank\">https://biblio.inscriptiones.org/epig10001707</a></li>  <li> Manganaro 1965 176 fig.5 <a href=\"https://biblio.inscriptiones.org/epig10001452\" target=\"_blank\">https://biblio.inscriptiones.org/epig10001452</a></li>  </ul>  <ul><li></li></ul>  "
    },
    {
      "id": "license",
      "html": " Licensed under a Creative Commons-Attribution 4.0 licence.  "
    }
  ],
  "images": [
    {
      "image": "ISic002946_tiled.tif",
      "thumb": "ISic002946_tiled-thumb.tif",
      "title": "I.Sicily with the permission of the Assessorato Regionale dei Beni Culturali e dell’Identità Siciliana - Dipartimento dei Beni Culturali e dell’Identità Siciliana"
    },
    {
      "image": "ISic002946.jpg",
      "thumb": "ISic002946-thumb.jpg",
      "title": "I.Sicily with the permission of the Assessorato Regionale dei Beni Culturali e dell’Identità Siciliana - Dipartimento dei Beni Culturali e dell’Identità Siciliana"
    }
  ]
}